rclib/utils/__init__.py
rclib/utils/dictionary.py
rclib/utils/errors/decorators.py
rclib/utils/errors/exceptions.py
rclib/utils/files/search.py
rcmanyutils-0.2.0.dist-info/METADATA
rcmanyutils-0.2.0.dist-info/WHEEL
rcmanyutils-0.2.0.dist-info/RECORD
