Metadata-Version: 2.4
Name: rcmanyutils
Version: 0.2.0
Summary: Various utilities for making python development easier
Project-URL: Homepage, https://github.com/RLC92/rcmanyutils
Project-URL: Issues, https://github.com/RLC92/rcmanyutils/issues
Requires-Python: >=3.13.1
Requires-Dist: pydantic>=2.9.2
Requires-Dist: type-lens>=0.2.3
